project5/__init__.py
project5-0.0.1.dist-info/METADATA
project5-0.0.1.dist-info/WHEEL
project5-0.0.1.dist-info/top_level.txt
project5-0.0.1.dist-info/RECORD
