Metadata-Version: 2.1
Name: project5
Version: 0.0.1
Summary: x
Author: x
